[{"sender":"anonymousguest","message":"Testing comments1","subNode":[{"sender":"anonymousguest","message":"Sendsun","subNode":[]}]},{"sender":"anonymousguest","message":"Tc2","subNode":[{"sender":"anonymousguest","message":"Xrf","subNode":[]},{"sender":"anonymousguest","message":"Under tc2 2","subNode":[{"sender":"anonymousguest","message":"Under tc2 Undef it","subNode":[]}]}]},{"sender":"aywriter","message":"Set","subNode":[]},{"sender":"aywriter","message":"Tc3","subNode":[{"sender":"anonymousguest","message":"Testing sub comments node","subNode":[]}]},{"sender":"anonymousguest","message":"sending comment","subNode":[]},{"sender":"anonymousguest","message":"sending comment","subNode":[]},{"sender":"commenter","message":"commentbody","subNode":[]},{"sender":"commenter","message":"commentbody","subNode":[]},{"sender":"anonymousguest","message":"Sendit","subNode":[]},{"sender":"anonymousguest","message":"Send","subNode":[]},{"sender":"anonymousguest","message":"Send","subNode":[]},{"sender":"anonymousguest","message":"Send3","subNode":[]},{"sender":"anonymousguest","message":"Hi People","uniqueTok":"NusQLHSL","timestamp":"Mon, Mar 29 '21 - 12:48:10","extras":"{}","subNode":[]}]